faiss_cpu_py36-1.7.3.dist-info/WHEEL
faiss_cpu_py36-1.7.3.dist-info/top_level.txt
faiss_cpu_py36-1.7.3.dist-info/LICENSE
faiss_cpu_py36-1.7.3.dist-info/RECORD
faiss_cpu_py36-1.7.3.dist-info/METADATA
faiss/swigfaiss_avx2.py
faiss/extra_wrappers.py
faiss/class_wrappers.py
faiss/_swigfaiss_avx2.cpython-36m-x86_64-linux-gnu.so
faiss/array_conversions.py
faiss/swigfaiss.i
faiss/python_callbacks.h
faiss/setup.py
faiss/gpu_wrappers.py
faiss/_swigfaiss.cpython-36m-x86_64-linux-gnu.so
faiss/__init__.py
faiss/swigfaiss.py
faiss/loader.py
faiss/contrib/datasets.py
faiss/contrib/inspect_tools.py
faiss/contrib/ondisk.py
faiss/contrib/torch_utils.py
faiss/contrib/client_server.py
faiss/contrib/exhaustive_search.py
faiss/contrib/factory_tools.py
faiss/contrib/vecs_io.py
faiss/contrib/evaluation.py
faiss/contrib/rpc.py
faiss/contrib/ivf_tools.py
faiss/contrib/clustering.py
faiss/contrib/__init__.py
faiss_cpu_py36.libs/libgfortran-040039e1.so.5.0.0
faiss_cpu_py36.libs/libquadmath-96973f99.so.0.0.0
faiss_cpu_py36.libs/libgomp-a34b3233.so.1.0.0
