Metadata-Version: 2.1
Name: faiss-cpu-py36
Version: 1.7.3
Summary: A library for efficient similarity search and clustering of dense vectors.
Home-page: https://github.com/victor-paltz/faiss-wheels-py36
Author: Kota Yamaguchi
Author-email: KotaYamaguchi1984@gmail.com
License: MIT
Keywords: search nearest neighbors
Classifier: Development Status :: 4 - Beta
Classifier: Intended Audience :: Developers
Classifier: Intended Audience :: Science/Research
Classifier: License :: OSI Approved :: MIT License
Classifier: Operating System :: MacOS :: MacOS X
Classifier: Operating System :: Microsoft :: Windows
Classifier: Operating System :: POSIX
Classifier: Programming Language :: Python :: 3.6
Classifier: Programming Language :: Python :: 3.7
Classifier: Programming Language :: Python :: 3.8
Classifier: Programming Language :: Python :: 3.9
Classifier: Programming Language :: Python :: 3.10
Classifier: Topic :: Scientific/Engineering :: Artificial Intelligence
License-File: LICENSE
